pyloadover/__init__.py
pyloadover/config.py
pyloadover/exceptions.py
pyloadover/functions/__init__.py
pyloadover/functions/context.py
pyloadover/functions/function.py
pyloadover/functions/id_generators.py
pyloadover/groups/__init__.py
pyloadover/groups/context.py
pyloadover/groups/function_validators.py
pyloadover/groups/group.py
pyloadover/manager.py
pyloadover/pyloadover.py
pyloadover/utils.py
pyloadover-3.2.1.dist-info/LICENSE
pyloadover-3.2.1.dist-info/METADATA
pyloadover-3.2.1.dist-info/WHEEL
pyloadover-3.2.1.dist-info/RECORD
