Metadata-Version: 2.1
Name: pyloadover
Version: 3.2.1
Summary: Overloading Utilities
License: LICENSE
Author: dav ost
Author-email: davidost2003@gmail.com
Requires-Python: >=3.8,<4.0
Classifier: License :: Other/Proprietary License
Classifier: Programming Language :: Python :: 3
Classifier: Programming Language :: Python :: 3.8
Classifier: Programming Language :: Python :: 3.9
Classifier: Programming Language :: Python :: 3.10
Classifier: Programming Language :: Python :: 3.11
Classifier: Programming Language :: Python :: 3.12
Requires-Dist: typeguard (>=4.3.0,<5.0.0)
